
<items>



<item>
<title>Corazon del Mar</title>
<link>$doregex[id]</link>
<regex>
<name>id</name>
<expres>file:'(.*)'</expres>
<page>http://streamin.to/embed-br5x06bkpcu4.html</page>
<referer>http://streamin.to</referer>
</regex>
<fanart>http://bajalogratis.com/wp-content/uploads/2016/02/En-el-coraz%C3%B3n-del-mar.jpg</fanart>
<thumbnail>http://bajalogratis.com/wp-content/uploads/2016/02/En-el-coraz%C3%B3n-del-mar.jpg</thumbnail>
<info></info>
</item>


<item>
<title>Ratchet and Clank</title>
<link>$doregex[id]</link>
<regex>
<name>id</name>
<expres>file:'(.*)'</expres>
<page>http://streamin.to/8xn6pbr566i9</page>
<referer>http://streamin.to</referer>
</regex>
<fanart>http://bajalogratis.com/wp-content/uploads/2016/08/Ratchet-y-Clank.jpg</fanart>
<thumbnail>http://bajalogratis.com/wp-content/uploads/2016/08/Ratchet-y-Clank.jpg</thumbnail>
<info></info>
</item>


<item>
<title>El Maestro del Dinero</title>
<link>$doregex[id]</link>
<regex>
<name>id</name>
<expres>file:'(.*)'</expres>
<page>http://streamin.to/embed-wun4yv8j17an.html</page>
<referer>http://streamin.to</referer>
</regex>
<fanart>http://bajalogratis.com/wp-content/uploads/2016/08/El-Maestro-Del-Dinero.jpg</fanart>
<thumbnail>http://bajalogratis.com/wp-content/uploads/2016/08/El-Maestro-Del-Dinero.jpg</thumbnail>
<info></info>
</item>


<item>
<title>El Experimento Filadelfia</title>
<link>$doregex[id]</link>
<regex>
<name>id</name>
<expres>file:'(.*)'</expres>
<pagehttp://streamin.to/embed-r4xf3d50cb1p.html</page>
<referer>http://streamin.to</referer>
</regex>
<fanart>https://ticotica.files.wordpress.com/2011/05/crepusculoamanecer12.jpg</fanart>
<thumbnail>https://ticotica.files.wordpress.com/2011/05/crepusculoamanecer12.jpg</thumbnail>
<info></info>
</item>

</items>
